{
    "neoforge:conditions": [
        {
            "type": "neoforge:mod_loaded",
            "modid": "twilightforest"
        }
    ],
    "type": "apotheosis:salvaging",
    "input": [
        {
            "item": "twilightforest:ironwood_helmet"
        },
        {
            "item": "twilightforest:ironwood_chestplate"
        },
        {
            "item": "twilightforest:ironwood_leggings"
        },
        {
            "item": "twilightforest:ironwood_boots"
        }
    ],
    "outputs": [
        {
            "max_count": 3,
            "min_count": 1,
            "stack": {
                "count": 1,
                "id": "twilightforest:ironwood_ingot"
            }
        }
    ]
}